fds/__init__.py
fds/sdk/__init__.py
fds/sdk/OPENOPTIMIZER/__init__.py
fds/sdk/OPENOPTIMIZER/api_client.py
fds/sdk/OPENOPTIMIZER/configuration.py
fds/sdk/OPENOPTIMIZER/exceptions.py
fds/sdk/OPENOPTIMIZER/model_utils.py
fds/sdk/OPENOPTIMIZER/rest.py
fds/sdk/OPENOPTIMIZER/api/__init__.py
fds/sdk/OPENOPTIMIZER/api/axioma_equity_portfolio_optimizer_api.py
fds/sdk/OPENOPTIMIZER/api/axioma_fixed_income_portfolio_optimizer_api.py
fds/sdk/OPENOPTIMIZER/api/barra_portfolio_optimizer_api.py
fds/sdk/OPENOPTIMIZER/api/fact_set_portfolio_optimizer_api.py
fds/sdk/OPENOPTIMIZER/api/northfield_portfolio_optimizer_api.py
fds/sdk/OPENOPTIMIZER/apis/__init__.py
fds/sdk/OPENOPTIMIZER/model/__init__.py
fds/sdk/OPENOPTIMIZER/model/afi_account_input.py
fds/sdk/OPENOPTIMIZER/model/afi_optimization_parameters.py
fds/sdk/OPENOPTIMIZER/model/afi_optimization_parameters_request.py
fds/sdk/OPENOPTIMIZER/model/afi_optimizer_strategy_input.py
fds/sdk/OPENOPTIMIZER/model/afi_optimizer_strategy_overrides_input.py
fds/sdk/OPENOPTIMIZER/model/archive_portfolio_output_type.py
fds/sdk/OPENOPTIMIZER/model/available_components_response.py
fds/sdk/OPENOPTIMIZER/model/available_components_response_data.py
fds/sdk/OPENOPTIMIZER/model/available_constraints_result_object.py
fds/sdk/OPENOPTIMIZER/model/available_constraints_result_object_data.py
fds/sdk/OPENOPTIMIZER/model/available_objectives_object.py
fds/sdk/OPENOPTIMIZER/model/available_strategies_input.py
fds/sdk/OPENOPTIMIZER/model/available_strategies_input_data.py
fds/sdk/OPENOPTIMIZER/model/available_strategies_response.py
fds/sdk/OPENOPTIMIZER/model/available_terms_object.py
fds/sdk/OPENOPTIMIZER/model/available_transcosts_result_object.py
fds/sdk/OPENOPTIMIZER/model/available_transcosts_result_object_data.py
fds/sdk/OPENOPTIMIZER/model/axp_account_input.py
fds/sdk/OPENOPTIMIZER/model/axp_available_components_input.py
fds/sdk/OPENOPTIMIZER/model/axp_available_components_input_data.py
fds_sdk_openoptimizer-0.0.1.dist-info/licenses/LICENSE
fds_sdk_openoptimizer-0.0.1.dist-info/METADATA
fds_sdk_openoptimizer-0.0.1.dist-info/WHEEL
fds_sdk_openoptimizer-0.0.1.dist-info/top_level.txt
fds_sdk_openoptimizer-0.0.1.dist-info/RECORD
